drnick/__init__.py
drnick-0.0.1.dist-info/LICENSE
drnick-0.0.1.dist-info/METADATA
drnick-0.0.1.dist-info/WHEEL
drnick-0.0.1.dist-info/top_level.txt
drnick-0.0.1.dist-info/RECORD
