Metadata-Version: 2.1
Name: drnick
Version: 0.0.1
Summary: Python DSL for logic programming with universal result quantification and effect delaying
Home-page: https://github.com/hamelin/drnick
Author: Benoit Hamelin
Author-email: benoit@benoithamelin.com
License: MIT
Platform: UNKNOWN
Requires-Python: >=3.7
